pydiscotool/__init__.py
pydiscotool/create_tfrecords_from_csv.py
pydiscotool/init.py
pydiscotool/tfrecords_creator.py
pydiscotool-cli/__init__.py
pydiscotool-cli/init.py
pydiscotool_cli-0.1.3.dist-info/LICENSE.txt
pydiscotool_cli-0.1.3.dist-info/METADATA
pydiscotool_cli-0.1.3.dist-info/WHEEL
pydiscotool_cli-0.1.3.dist-info/entry_points.txt
pydiscotool_cli-0.1.3.dist-info/top_level.txt
pydiscotool_cli-0.1.3.dist-info/RECORD
